RlEvaluation/__init__.py
RlEvaluation/_utils/__init__.py
RlEvaluation/_utils/data.py
RlEvaluation/_utils/jit.py
RlEvaluation/_utils/logging.py
RlEvaluation/_utils/numba.py
RlEvaluation/_utils/numpy.py
RlEvaluation/backend/statistics.py
RlEvaluation/backend/temporal.py
RlEvaluation/config.py
RlEvaluation/hypers/__init__.py
RlEvaluation/hypers/api.py
RlEvaluation/hypers/interface.py
RlEvaluation/hypers/reporting.py
RlEvaluation/hypers/simulation.py
RlEvaluation/hypers/utils.py
RlEvaluation/interpolation.py
RlEvaluation/intervals.py
RlEvaluation/metrics.py
RlEvaluation/py.typed
RlEvaluation/statistics.py
RlEvaluation/temporal.py
RlEvaluation/utils/__init__.py
RlEvaluation/utils/math.py
RlEvaluation/utils/pandas.py
RlEvaluation-1.3.1.dist-info/WHEEL
RlEvaluation-1.3.1.dist-info/METADATA
RlEvaluation-1.3.1.dist-info/RECORD
