Metadata-Version: 2.1
Name: RlEvaluation
Version: 1.3.1
License: MIT
Author-email: Andy Patterson <andnpatterson@gmail.com>
Requires-Python: >=3.11
Requires-Dist: numba>=0.57.0
Requires-Dist: numpy>=1.23.5
Requires-Dist: pandas>=1.5.3
Requires-Dist: scipy>=1.9.3
